libopl/__init__.py
libopl/api.py
libopl/artwork.py
libopl/common.py
libopl/game.py
libopl/opl.py
libopl/ul.py
libopl-0.1.2.dist-info/LICENSE
libopl-0.1.2.dist-info/METADATA
libopl-0.1.2.dist-info/WHEEL
libopl-0.1.2.dist-info/entry_points.txt
libopl-0.1.2.dist-info/top_level.txt
libopl-0.1.2.dist-info/RECORD
