Metadata-Version: 2.1
Name: libopl
Version: 0.1.2
Summary: Library And Tool To Manage Open-PS2-Loader USB-Drives & Games
Home-page: https://github.com/nold360/libopl
Author: Nold
Author-email: nold@gnu.one
License: UNKNOWN
Platform: UNKNOWN
Classifier: Programming Language :: Python :: 3
Classifier: License :: OSI Approved :: GNU General Public License v3 or later (GPLv3+)
Classifier: Operating System :: POSIX :: Linux
Classifier: Environment :: Console
